agentkit_gf/__init__.py
agentkit_gf/_base_agent.py
agentkit_gf/delegating_tools_agent.py
agentkit_gf/soft_tool_agent.py
agentkit_gf/tools/__init__.py
agentkit_gf/tools/agent.py
agentkit_gf/tools/builtin_tools_matrix.py
agentkit_gf/tools/fs.py
agentkit_gf/tools/os.py
agentkit_gf-0.1.5.dist-info/licenses/LICENSE
agentkit_gf-0.1.5.dist-info/METADATA
agentkit_gf-0.1.5.dist-info/WHEEL
agentkit_gf-0.1.5.dist-info/top_level.txt
agentkit_gf-0.1.5.dist-info/RECORD
