Metadata-Version: 2.4
Name: agentkit-gf
Version: 0.1.5
Summary: Lightweight agents on top of Pydantic AI with true soft tools and conversation history
Author-email: GreenFuze <info@greenfuze.com>
Maintainer-email: GreenFuze <info@greenfuze.com>
License-Expression: MIT
Project-URL: Homepage, https://github.com/GreenFuze/agentkit-gf
Project-URL: Repository, https://github.com/GreenFuze/agentkit-gf
Project-URL: Documentation, https://github.com/GreenFuze/agentkit-gf#readme
Project-URL: Issues, https://github.com/GreenFuze/agentkit-gf/issues
Keywords: ai,agent,pydantic,openai,tools,soft-tools
Classifier: Development Status :: 3 - Alpha
Classifier: Intended Audience :: Developers
Classifier: Operating System :: OS Independent
Classifier: Programming Language :: Python :: 3
Classifier: Programming Language :: Python :: 3.11
Classifier: Programming Language :: Python :: 3.12
Classifier: Topic :: Scientific/Engineering :: Artificial Intelligence
Classifier: Topic :: Software Development :: Libraries :: Python Modules
Requires-Python: >=3.11
License-File: LICENSE
Requires-Dist: pydantic-ai>=0.8.1
Requires-Dist: pydantic>=2.0.0
Provides-Extra: dev
Requires-Dist: pytest>=7.0.0; extra == "dev"
Requires-Dist: pytest-asyncio>=0.21.0; extra == "dev"
Requires-Dist: black>=23.0.0; extra == "dev"
Requires-Dist: isort>=5.12.0; extra == "dev"
Requires-Dist: flake8>=6.0.0; extra == "dev"
Requires-Dist: mypy>=1.0.0; extra == "dev"
Dynamic: license-file
